lmfpy.cpython-36m-x86_64-linux-gnu.so
lmfpy-20180327.dist-info/WHEEL
lmfpy-20180327.dist-info/top_level.txt
lmfpy-20180327.dist-info/RECORD
lmfpy-20180327.dist-info/METADATA
